[
    {
        "0": "Ant Financial\n",
        "1": "Bytedance\n",
        "2": "DiDi\n",
        "3": "Airbnb\n",
        "4": "Stripe\n",
        "5": "SpaceX\n",
        "6": "Lufax\n",
        "7": "JUUL Labs\n",
        "8": "Cainiao\n",
        "9": "Palantir Technologies\n",
        "10": "Kuaishou\n",
        "11": "Paytm\n",
        "12": "DJI\n",
        "13": "Epic Games\n",
        "14": "Grab\n",
        "15": "Lianjia (Homelink)\n",
        "16": "Wish (fka ContextLogic)\n",
        "17": "Jiedaibao\n",
        "18": "Nubank\n",
        "19": "OYO\n",
        "20": "Go-Jek\n",
        "21": "Ola Cabs\n",
        "22": "WeBank\n",
        "23": "Coupang\n",
        "24": "PingAn Health Insurance Tech\n",
        "25": "Coinbase\n",
        "26": "OneConnect\n",
        "27": "Robinhood\n",
        "28": "Instacart\n",
        "29": "JD Finance\n",
        "30": "DoorDash\n",
        "31": "Tokopedia\n",
        "32": "Roivant Sciences\n",
        "33": "UiPath Inc.\n",
        "34": "WeWork\n",
        "35": "Tanium\n",
        "36": "Compass\n",
        "37": "Farfetch\n",
        "38": "Databricks\n",
        "39": "Klarna\n",
        "40": "Byju's\n",
        "41": "Rivian\n",
        "42": "CloudKitchens\n",
        "43": "Bluehole\n",
        "44": "United Imaging Healthcare\n",
        "45": "Magic Leap\n",
        "46": "Zenefits\n",
        "47": "Meizu\n",
        "48": "SoFi\n",
        "49": "BAIC BJEV\n",
        "50": "Yello Mobile\n",
        "51": "Megvii\n",
        "52": "Ginkgo Bioworks\n",
        "53": "TripActions\n",
        "54": "UBtech Robotics\n",
        "55": "Niantic\n",
        "56": "Opendoor\n",
        "57": "Garena\n",
        "58": "Root Insurance Co\n",
        "59": "Shouqi Car Rental\n",
        "60": "N26\n",
        "61": "TransferWise\n",
        "62": "Credit Karma\n",
        "63": "Swiggy\n",
        "64": "Rubrik\n",
        "65": "e-Shang Redwood\n",
        "66": "Canva\n",
        "67": "Oscar Health\n",
        "68": "Zoox (company)\n",
        "69": "Fanatics\n",
        "70": "Rappi\n",
        "71": "Automattic\n",
        "72": "VIPKID\n",
        "73": "AliMusic\n",
        "74": "Jia.com\n",
        "75": "LY.com\n",
        "76": "Meili United Group\n",
        "77": "Ping An Good Doctor\n",
        "78": "Royole Corporation\n",
        "79": "VANCL\n",
        "80": "Wanda E-commerce\n",
        "81": "Yixia Technology\n",
        "82": "Affirm\n",
        "83": "OVO\n",
        "84": "OakNorth\n",
        "85": "UnionPay\n",
        "86": "Udaan\n",
        "87": "Bird\n",
        "88": "Convoy\n",
        "89": "GitLab\n",
        "90": "Toast\n",
        "91": "Plaid\n",
        "92": "Brex\n",
        "93": "AmWINS Group\n",
        "94": "Woowa Brothers\n",
        "95": "Vice Media\n",
        "96": "Bukalapak\n",
        "97": "Monzo\n",
        "98": "Confluent\n",
        "99": "Cambricon\n",
        "100": "Roblox\n",
        "101": "Zomato\n",
        "102": "Zhihu\n",
        "103": "Kingsoft Cloud\n",
        "104": "LimeBike\n",
        "105": "Mozido\n",
        "106": "Houzz\n",
        "107": "Babytree\n",
        "108": "Viva Republica\n",
        "109": "Taobao Movie\n",
        "110": "Nextdoor\n",
        "111": "Three Squirrels\n",
        "112": "Babylon Health\n",
        "113": "FlixMobility\n",
        "114": "Applovin\n",
        "115": "Beijing Weiying Technology\n",
        "116": "Deliveroo\n",
        "117": "Domo\n",
        "118": "Firstp2p\n",
        "119": "Huimin.cn\n",
        "120": "Meicai.cn\n",
        "121": "Maoyan-Weiying\n",
        "122": "Oxford Nanopore Technologies\n",
        "123": "ReNew Power\n",
        "124": "Sensetime\n",
        "125": "SurveyMonkey\n",
        "126": "Taopiaopiao\n",
        "127": "Traveloka\n",
        "128": "Trendy International Group\n",
        "129": "Tubatu.com\n",
        "130": "Youxinpai\n",
        "131": "Marqeta\n",
        "132": "Avant\n",
        "133": "ThoughtSpot\n",
        "134": "Intarcia Therapeutics\n",
        "135": "Yinlong Group\n",
        "136": "Youxia Motors\n",
        "137": "Sanpower Group\n",
        "138": "Monday.com\n",
        "139": "Dfinity\n",
        "140": "Prosper Marketplace\n",
        "141": "RigUp\n",
        "142": "Musinsa\n",
        "143": "Postmates\n",
        "144": "Apus Group\n",
        "145": "BenevolentAI\n",
        "146": "Avito.ru\n",
        "147": "Billdesk\n",
        "148": "Ucommune\n",
        "149": "Crystal Lagoons\n",
        "150": "NantOmics\n",
        "151": "Reddit\n",
        "152": "Quora\n",
        "153": "Sprinklr\n",
        "154": "Zocdoc\n",
        "155": "L&P Cosmetic\n",
        "156": "23andMe\n",
        "157": "Thumbtack\n",
        "158": "Carta\n",
        "159": "PAX Labs\n",
        "160": "Revolut\n",
        "161": "Taihe Music Group\n",
        "162": "Squarespace\n",
        "163": "The Honest Company\n",
        "164": "Delhivery\n",
        "165": "AIWAYS\n",
        "166": "Caocao Zhuanche\n",
        "167": "Northvolt\n",
        "168": "BlaBlaCar\n",
        "169": "Afiniti\n",
        "170": "HeartFlow\n",
        "171": "Proteus Digital Health\n",
        "172": "Chime\n",
        "173": "Gett\n",
        "174": "Musigma\n",
        "175": "Dream11\n",
        "176": "Aihuishou\n",
        "177": "Asana\n",
        "178": "Spring Rain Software\n",
        "179": "Douyu TV\n",
        "180": "Lakala\n",
        "181": "Ninebot\n",
        "182": "Souche\n",
        "183": "UCloud\n",
        "184": "Tujia.com\n",
        "185": "ZBJ.com\n",
        "186": "Snowflake Computing\n",
        "187": "Letgo\n",
        "188": "Duolingo\n",
        "189": "Hello Bike\n",
        "190": "Suning Sports\n",
        "191": "Tuandaiwang\n",
        "192": "Koudai Gouwu\n",
        "193": "Symphony\n",
        "194": "Dataiku\n",
        "195": "Away\n",
        "196": "C3 IoT\n",
        "197": "Hike Messenger\n",
        "198": "Wemakeprice\n",
        "199": "GPClub\n",
        "200": "Knotel\n",
        "201": "OneTrust\n",
        "202": "ETCP\n",
        "203": "Kr Space\n",
        "204": "PagerDuty\n",
        "205": "10x Genomics\n",
        "206": "Alisports\n",
        "207": "Loji Logistics\n",
        "208": "KeepTruckin\n",
        "209": "ezCater\n",
        "210": "Iwjw\n",
        "211": "Darktrace\n",
        "212": "Fair\n",
        "213": "Big Basket\n",
        "214": "Glossier\n",
        "215": "Bitmain\n",
        "216": "Byton\n",
        "217": "EasyLife Financial Services\n",
        "218": "Dada\n",
        "219": "Warby Parker\n",
        "220": "NetEase Cloud Music\n",
        "221": "Doctolib\n",
        "222": "SentinelOne\n",
        "223": "Sisense\n",
        "224": "Wheels Up\n",
        "225": "SmartNews\n",
        "226": "Outreach\n",
        "227": "Casper\n",
        "228": "NetEase Youdao\n",
        "229": "Luoji Siwei\n",
        "230": "Global Fashion Group\n",
        "231": "Rivigo\n",
        "232": "Trax\n",
        "233": "TuSimple\n",
        "234": "Ualá\n",
        "235": "Vinted\n",
        "236": "Instabase\n",
        "237": "Aprogen\n",
        "238": "Grammarly\n",
        "239": "IronSource\n",
        "240": "Acronis\n",
        "241": "Frontline Education\n",
        "242": "Icertis\n",
        "243": "Sonder\n",
        "244": "StockX\n",
        "245": "Meero\n",
        "246": "Ivalua\n",
        "247": "Auth0\n",
        "248": "Sumo Logic\n",
        "249": "Klook\n",
        "250": "Coursera\n",
        "251": "Airwallex\n",
        "252": "Bill.com\n",
        "253": "Cloudflare\n",
        "254": "InMobi\n",
        "255": "Maimai\n",
        "256": "Yanolja\n",
        "257": "Shape Security\n",
        "258": "Lightricks\n",
        "259": "Age of Learning, Inc.\n",
        "260": "Branch Metrics\n",
        "261": "VTS\n",
        "262": "Policy Bazaar\n",
        "263": "Rent the Runway\n",
        "264": "Pine Lab\n",
        "265": "Vlocity\n",
        "266": "JD Indonesia\n",
        "267": "WalkMe\n",
        "268": "Beibei\n",
        "269": "OCSiAl\n",
        "270": "OutSystems\n",
        "271": "Chubao Technology\n",
        "272": "Dt Dream\n",
        "273": "DXY\n",
        "274": "Futu Securities\n",
        "275": "FXiaoKe\n",
        "276": "Fangdd.com\n",
        "277": "Fanli\n",
        "278": "Huikedu Group\n",
        "279": "Gusto\n",
        "280": "Snapdeal\n",
        "281": "Netskope\n",
        "282": "iCarbonX\n",
        "283": "Innovent Biologics\n",
        "284": "iTutorGroup\n",
        "285": "JFrog\n",
        "286": "Jiangsu Zimi Technology\n",
        "287": "Jollychic\n",
        "288": "Lalamove\n",
        "289": "Lamabang\n",
        "290": "Mia.com\n",
        "291": "Careem\n",
        "292": "MissFresh\n",
        "293": "Mobvoi\n",
        "294": "Mofang Apartment\n",
        "295": "Novogene\n",
        "296": "QingCloud\n",
        "297": "Seismic Software\n",
        "298": "Smartmi\n",
        "299": "Tongdun Technology\n",
        "300": "Unisound\n",
        "301": "Wacai.com\n",
        "302": "Wifi Master Key\n",
        "303": "CrowdStrike\n",
        "304": "Womai\n",
        "305": "Xiaozhu.com\n",
        "306": "YH Global\n",
        "307": "Yuanfudao\n",
        "308": "Vox Media\n",
        "309": "Yitu Technology\n",
        "310": "Yidian Zixun\n",
        "311": "Essential Products\n",
        "312": "MindMaze\n",
        "313": "Zhaogang.com\n",
        "314": "Zhuanzhuan\n",
        "315": "Zuoyebang\n",
        "316": "17Zuoye\n",
        "317": "GoGoVan\n",
        "318": "Rubicon Global\n",
        "319": "36Kr Media\n",
        "320": "InVision\n",
        "321": "58 Daojia\n",
        "322": "Lookout Security\n",
        "323": "Kabam\n",
        "324": "9fbank.com\n",
        "325": "Udacity\n",
        "326": "LinkSure Network (WiFi Master Key)\n",
        "327": "MedMen\n",
        "328": "OrCam\n",
        "329": "Improbable\n",
        "330": "Bolt\n",
        "331": "One Medical\n",
        "332": "Talkdesk\n",
        "333": "Tresata\n",
        "334": "AppDirect\n",
        "335": "Nearmap\n",
        "336": "Collibra\n",
        "337": "Prometheus Group\n",
        "338": "team.blue (merge of Combell Group and TransIP Group)\n",
        "339": "Druva\n",
        "340": "CitiusTech\n",
        "341": "Ola Electric\n",
        "342": "Icertis\n",
        "343": "HighRadius\n",
        "344": "Scale AI\n",
        "345": "Grove Collaborative\n",
        "346": "Freshworks\n",
        "347": "Turo\n"
    },
    {
        "0": "150\n",
        "1": "78.0\n",
        "2": "51.6\n",
        "3": "38.0\n",
        "4": "35.0\n",
        "5": "36\n",
        "6": "30.0\n",
        "7": "24.0\n",
        "8": "20.0\n",
        "9": "20.0\n",
        "10": "18.0\n",
        "11": "18.0\n",
        "12": "15.0\n",
        "13": "15.0\n",
        "14": "14.0\n",
        "15": "13.0\n",
        "16": "11.0+\n",
        "17": "10.77\n",
        "18": "10.0+\n",
        "19": "10.0\n",
        "20": "10.0\n",
        "21": "10\n",
        "22": "9.23\n",
        "23": "9.0\n",
        "24": "8.8\n",
        "25": "8.0\n",
        "26": "8.0\n",
        "27": "7.6\n",
        "28": "7.6\n",
        "29": "7.3\n",
        "30": "7.1\n",
        "31": "7.0\n",
        "32": "7.0\n",
        "33": "7.0\n",
        "34": "7\n",
        "35": "6.5\n",
        "36": "6.4\n",
        "37": "6.2\n",
        "38": "6.2\n",
        "39": "5.5\n",
        "40": "5.4\n",
        "41": "5.0+\n",
        "42": "5.0\n",
        "43": "5.0\n",
        "44": "5.0\n",
        "45": "4.5\n",
        "46": "4.5\n",
        "47": "4.4\n",
        "48": "4.3\n",
        "49": "4.2\n",
        "50": "4.05\n",
        "51": "4.0+\n",
        "52": "4.0\n",
        "53": "4.0\n",
        "54": "4.0\n",
        "55": "3.95\n",
        "56": "3.8\n",
        "57": "3.7\n",
        "58": "3.65\n",
        "59": "3.55\n",
        "60": "3.5\n",
        "61": "3.5\n",
        "62": "3.5\n",
        "63": "3.3\n",
        "64": "3.3\n",
        "65": "3.25\n",
        "66": "3.2\n",
        "67": "3.2\n",
        "68": "3.2\n",
        "69": "3.17\n",
        "70": "3+\n",
        "71": "3.0\n",
        "72": "3.0\n",
        "73": "3.0\n",
        "74": "3.0\n",
        "75": "3.0\n",
        "76": "3.0\n",
        "77": "3.0\n",
        "78": "3.0\n",
        "79": "3.0\n",
        "80": "3.0\n",
        "81": "3.0\n",
        "82": "2.9\n",
        "83": "2.9\n",
        "84": "2.8\n",
        "85": "2.8\n",
        "86": "2.8\n",
        "87": "2.775\n",
        "88": "2.75\n",
        "89": "2.75\n",
        "90": "2.7\n",
        "91": "2.65\n",
        "92": "2.6\n",
        "93": "2.6\n",
        "94": "2.6\n",
        "95": "2.55\n",
        "96": "2.5\n",
        "97": "2.5\n",
        "98": "2.5\n",
        "99": "2.5\n",
        "100": "2.5\n",
        "101": "3.0\n",
        "102": "2.5\n",
        "103": "2.4\n",
        "104": "2.4\n",
        "105": "2.39\n",
        "106": "2.32\n",
        "107": "2.19\n",
        "108": "2.2\n",
        "109": "2.1\n",
        "110": "2.1\n",
        "111": "2.09\n",
        "112": "2.0+\n",
        "113": "2.0+\n",
        "114": "2.0\n",
        "115": "2.0\n",
        "116": "2.0\n",
        "117": "2.0\n",
        "118": "2.0\n",
        "119": "2.0\n",
        "120": "2.0\n",
        "121": "2.0\n",
        "122": "2.0\n",
        "123": "2.0\n",
        "124": "2.0\n",
        "125": "2.0\n",
        "126": "2.0\n",
        "127": "2.0\n",
        "128": "2.0\n",
        "129": "2.0\n",
        "130": "2.0\n",
        "131": "2.0-\n",
        "132": "1.98\n",
        "133": "1.95\n",
        "134": "1.95\n",
        "135": "1.95\n",
        "136": "1.94\n",
        "137": "1.93\n",
        "138": "1.9\n",
        "139": "1.9\n",
        "140": "1.9\n",
        "141": "1.9\n",
        "142": "1.89\n",
        "143": "1.85\n",
        "144": "1.85\n",
        "145": "1.85\n",
        "146": "1.82\n",
        "147": "1.8\n",
        "148": "1.8\n",
        "149": "1.8\n",
        "150": "1.8\n",
        "151": "3.0\n",
        "152": "1.8\n",
        "153": "1.8\n",
        "154": "1.8\n",
        "155": "1.78\n",
        "156": "1.75\n",
        "157": "1.7\n",
        "158": "1.7\n",
        "159": "1.7\n",
        "160": "1.7\n",
        "161": "1.7\n",
        "162": "1.7\n",
        "163": "1.7\n",
        "164": "1.6\n",
        "165": "1.6\n",
        "166": "1.6\n",
        "167": "1.6\n",
        "168": "1.6\n",
        "169": "1.6\n",
        "170": "1.5+\n",
        "171": "1.5\n",
        "172": "1.5\n",
        "173": "1.5\n",
        "174": "1.5\n",
        "175": "1.5\n",
        "176": "1.5\n",
        "177": "1.5\n",
        "178": "1.5\n",
        "179": "1.5\n",
        "180": "1.5\n",
        "181": "1.5\n",
        "182": "1.5\n",
        "183": "1.5\n",
        "184": "1.5\n",
        "185": "1.5\n",
        "186": "1.5\n",
        "187": "1.5\n",
        "188": "1.5\n",
        "189": "1.47\n",
        "190": "1.47\n",
        "191": "1.46\n",
        "192": "1.45\n",
        "193": "1.4\n",
        "194": "1.4\n",
        "195": "1.4\n",
        "196": "1.4\n",
        "197": "1.4\n",
        "198": "1.33\n",
        "199": "1.32\n",
        "200": "1.3\n",
        "201": "1.3\n",
        "202": "1.3\n",
        "203": "1.3\n",
        "204": "1.3\n",
        "205": "1.28\n",
        "206": "1.27\n",
        "207": "1.26\n",
        "208": "1.25\n",
        "209": "1.25\n",
        "210": "1.25\n",
        "211": "1.25\n",
        "212": "1.2\n",
        "213": "1.2\n",
        "214": "1.2\n",
        "215": "1.2\n",
        "216": "1.2\n",
        "217": "1.2\n",
        "218": "1.2\n",
        "219": "1.2\n",
        "220": "1.16\n",
        "221": "1.13\n",
        "222": "1.1\n",
        "223": "1.1\n",
        "224": "1.1\n",
        "225": "1.1\n",
        "226": "1.1\n",
        "227": "1.1\n",
        "228": "1.1\n",
        "229": "1.1\n",
        "230": "1.1\n",
        "231": "1.05\n",
        "232": "1.1\n",
        "233": "1.095\n",
        "234": "1\n",
        "235": "1.4\n",
        "236": "1.05\n",
        "237": "1.04\n",
        "238": "1+\n",
        "239": "1+\n",
        "240": "1+\n",
        "241": "1+\n",
        "242": "1+\n",
        "243": "1+\n",
        "244": "1+\n",
        "245": "1+\n",
        "246": "1+\n",
        "247": "1+\n",
        "248": "1+\n",
        "249": "1+\n",
        "250": "1+\n",
        "251": "1+\n",
        "252": "1+\n",
        "253": "1+\n",
        "254": "1+\n",
        "255": "1+\n",
        "256": "1+\n",
        "257": "1.0\n",
        "258": "1.0\n",
        "259": "1.0\n",
        "260": "1.0\n",
        "261": "1.0\n",
        "262": "1.0\n",
        "263": "1.0\n",
        "264": "1.0\n",
        "265": "1.0\n",
        "266": "1.0\n",
        "267": "1.0\n",
        "268": "1\n",
        "269": "1\n",
        "270": "1\n",
        "271": "1\n",
        "272": "1\n",
        "273": "1\n",
        "274": "1\n",
        "275": "1\n",
        "276": "1\n",
        "277": "1\n",
        "278": "1\n",
        "279": "1\n",
        "280": "1.0\n",
        "281": "2.8+\n",
        "282": "1\n",
        "283": "1\n",
        "284": "1\n",
        "285": "1\n",
        "286": "1\n",
        "287": "1\n",
        "288": "1\n",
        "289": "1\n",
        "290": "1\n",
        "291": "1\n",
        "292": "1\n",
        "293": "1\n",
        "294": "1\n",
        "295": "1\n",
        "296": "1\n",
        "297": "1\n",
        "298": "1\n",
        "299": "1\n",
        "300": "1\n",
        "301": "1\n",
        "302": "1\n",
        "303": "1\n",
        "304": "1\n",
        "305": "1\n",
        "306": "1\n",
        "307": "1\n",
        "308": "1\n",
        "309": "1\n",
        "310": "1\n",
        "311": "1\n",
        "312": "1\n",
        "313": "1\n",
        "314": "1\n",
        "315": "1\n",
        "316": "1\n",
        "317": "1\n",
        "318": "1\n",
        "319": "1\n",
        "320": "1\n",
        "321": "1\n",
        "322": "1\n",
        "323": "1\n",
        "324": "1\n",
        "325": "1\n",
        "326": "1\n",
        "327": "1\n",
        "328": "1\n",
        "329": "1\n",
        "330": "1\n",
        "331": "1\n",
        "332": "1\n",
        "333": "1\n",
        "334": "1\n",
        "335": "1\n",
        "336": "5+\n",
        "337": "1\n",
        "338": "1\n",
        "339": "1\n",
        "340": "1+\n",
        "341": "1+\n",
        "342": "1+\n",
        "343": "1\n",
        "344": "1+\n",
        "345": "1+\n",
        "346": "1.5+\n",
        "347": "1+\n"
    },
    {
        "0": "April 2018[11]\n",
        "1": "November 2018[12]\n",
        "2": "December 2018[13]\n",
        "3": "March 2018[14]\n",
        "4": "September 2019[15]\n",
        "5": "May 2019[16]\n",
        "6": "June 2018[17]\n",
        "7": "October 2019[18]\n",
        "8": "September 2017[17]\n",
        "9": "November 2018[19]\n",
        "10": "April 2018[17]\n",
        "11": "March 2019[20]\n",
        "12": "September 2016[1]\n",
        "13": "October 2018[1]\n",
        "14": "March 2019[21]\n",
        "15": "September 2018[22]\n",
        "16": "August 2019[23][5][1][24]\n",
        "17": "March 2018[25]\n",
        "18": "July 2019[26][27]\n",
        "19": "June 2019[28]\n",
        "20": "April 2019[29]\n",
        "21": "October 2019[30]\n",
        "22": "March 2018[25]\n",
        "23": "March 2018[31]\n",
        "24": "March 2018[25]\n",
        "25": "October 2018[32]\n",
        "26": "February 2018[17]\n",
        "27": "July 2019[33][34]\n",
        "28": "October 2018[35]\n",
        "29": "January 2016[17]\n",
        "30": "February 2019[36]\n",
        "31": "December 2018[37]\n",
        "32": "November 2018[38]\n",
        "33": "March 2019 [39]\n",
        "34": "November 2019[40]\n",
        "35": "October 2018[41]\n",
        "36": "July 2019[42][43]\n",
        "37": "September 2018[44]\n",
        "38": "October 2019[45]\n",
        "39": "August 2019[46][5][47]\n",
        "40": "October 2018[48][49]\n",
        "41": "September 2019[citation needed]\n",
        "42": "November 2019[50][51]\n",
        "43": "March 2018[31]\n",
        "44": "September 2017[17]\n",
        "45": "February 2016[1][5]\n",
        "46": "May 2015[2][5]\n",
        "47": "October 2016[17]\n",
        "48": "May 2019[5][52]\n",
        "49": "August 2017[17]\n",
        "50": "November 2016[5][53]\n",
        "51": "May 2019[54]\n",
        "52": "September 2019[55]\n",
        "53": "June 2019[56][57]\n",
        "54": "November 2017[17]\n",
        "55": "January 2019[58]\n",
        "56": "March 2019[5][59][60]\n",
        "57": "September 2016[5]\n",
        "58": "September 2019[61]\n",
        "59": "December 2016[17]\n",
        "60": "July 2019[62]\n",
        "61": "May 2019[63][64]\n",
        "62": "June 2015[1][2][5]\n",
        "63": "December 2018[65][66]\n",
        "64": "Jan 2019[67]\n",
        "65": "July 2017[17]\n",
        "66": "October 2019[68]\n",
        "67": "March 2018[69]\n",
        "68": "July, 2018[70]\n",
        "69": "August 2015[5]\n",
        "70": "April 2019[71]\n",
        "71": "September 2019[72]\n",
        "72": "June 2018[73]\n",
        "73": "September 2016[17]\n",
        "74": "February 2015[17]\n",
        "75": "August 2016[17]\n",
        "76": "November 2015[17]\n",
        "77": "May 2016[5]\n",
        "78": "November 2016[5]\n",
        "79": "February 2014[5]\n",
        "80": "January 2015[5]\n",
        "81": "November 2016[17]\n",
        "82": "April 2019[74][75]\n",
        "83": "October 2019[76]\n",
        "84": "February 2019[77]\n",
        "85": "October 2016[17]\n",
        "86": "August 2019[78]\n",
        "87": "October 2019[79]\n",
        "88": "November 2019[80]\n",
        "89": "September 2019[81][82]\n",
        "90": "March 2019[83][84]\n",
        "91": "December 2018[85]\n",
        "92": "June 2019[86][87]\n",
        "93": "October 2016[88]\n",
        "94": "March 2018[31]\n",
        "95": "December 2015[5]\n",
        "96": "October 2019[89]\n",
        "97": "June 2019[90]\n",
        "98": "January 2019[91]\n",
        "99": "June 2018[17]\n",
        "100": "September 2018[92]\n",
        "101": "Jan 2020[93]\n",
        "102": "August 2018[17]\n",
        "103": "January 2018[17]\n",
        "104": "August 2019[94]\n",
        "105": "October 2014[5]\n",
        "106": "October 2014[5]\n",
        "107": "June 2018[17]\n",
        "108": "December 2018[95]\n",
        "109": "May 2016[5]\n",
        "110": "May 2019[96]\n",
        "111": "September 2015[17]\n",
        "112": "August 2019[97]\n",
        "113": "August 2019[98]\n",
        "114": "July 2018[99]\n",
        "115": "April 2016[5]\n",
        "116": "September 2017[100]\n",
        "117": "March 2016[5][101]\n",
        "118": "September 2016[5]\n",
        "119": "September 2016[17]\n",
        "120": "June 2016[17]\n",
        "121": "November 2017[17]\n",
        "122": "November 2012[102]\n",
        "123": "February 2017[103]\n",
        "124": "December 2017[17]\n",
        "125": "August 2018[104]\n",
        "126": "July 2017[17]\n",
        "127": "February 2018[105]\n",
        "128": "February 2012[5][106]\n",
        "129": "March 2015[17]\n",
        "130": "January 2017[17]\n",
        "131": "May 2019[107]\n",
        "132": "September 2015[5]\n",
        "133": "August 2019[108][109]\n",
        "134": "September 2016[5]\n",
        "135": "December 2016[17]\n",
        "136": "March 2018[17]\n",
        "137": "March 2018[17]\n",
        "138": "July 2019[110]\n",
        "139": "August 2018[111]\n",
        "140": "August 2015[5]\n",
        "141": "October 2019[citation needed]\n",
        "142": "November 2019[112]\n",
        "143": "January 2019[113]\n",
        "144": "August 2017[17]\n",
        "145": "August 2015[5]\n",
        "146": "February 2014[5][114]\n",
        "147": "November 2018[115]\n",
        "148": "August 2018[17]\n",
        "149": "September 2009[116]\n",
        "150": "June 2015[5]\n",
        "151": "February 2019[117]\n",
        "152": "April 2017[118]\n",
        "153": "July 2016[5]\n",
        "154": "August 2015[5]\n",
        "155": "March 2018[112]\n",
        "156": "September 2017[119]\n",
        "157": "July 2019[120][2]\n",
        "158": "May 2019[121]\n",
        "159": "April 2019[122]\n",
        "160": "April 2018[123]\n",
        "161": "June 2018[17]\n",
        "162": "December 2017[124]\n",
        "163": "August 2015[125]\n",
        "164": "March 2019[126][127]\n",
        "165": "April 2018[17]\n",
        "166": "Jan 2018[17]\n",
        "167": "June 2019[5]\n",
        "168": "August 2016[5]\n",
        "169": "May 2017[128]\n",
        "170": "February 2018[129]\n",
        "171": "February 2016[130]\n",
        "172": "March 2019[131]\n",
        "173": "May 2019[132]\n",
        "174": "February 2013[133]\n",
        "175": "April 2019[134]\n",
        "176": "January 2018[17]\n",
        "177": "November 2018[135]\n",
        "178": "June 2016[17]\n",
        "179": "March 2018[17]\n",
        "180": "June 2015[17]\n",
        "181": "October 2017[17]\n",
        "182": "November 2017[17]\n",
        "183": "June 2018[17]\n",
        "184": "October 2017[136][137]\n",
        "185": "June 2015[17]\n",
        "186": "Jan 2018[138]\n",
        "187": "August 2018[139]\n",
        "188": "December 2019[140]\n",
        "189": "June 2018[17]\n",
        "190": "July 2018[17]\n",
        "191": "May 2017[17]\n",
        "192": "October 2014[17]\n",
        "193": "June 2019[141][142]\n",
        "194": "December 2019[143]\n",
        "195": "May 2019[144]\n",
        "196": "March 2017[145]\n",
        "197": "August 2016[103]\n",
        "198": "September 2015[112]\n",
        "199": "December 2018[112]\n",
        "200": "August 2019[146]\n",
        "201": "July 2019[147]\n",
        "202": "October 2016[17]\n",
        "203": "June 2018[17]\n",
        "204": "September 2018[148]\n",
        "205": "January 2019[149]\n",
        "206": "April 2018[17]\n",
        "207": "May 2015[17]\n",
        "208": "April 2019[150]\n",
        "209": "April 2019[151]\n",
        "210": "November 2015[17]\n",
        "211": "May 2018[152]\n",
        "212": "December 2018[153]\n",
        "213": "March 2019[154]\n",
        "214": "March 2019[155]\n",
        "215": "August 2018[17]\n",
        "216": "June 2018[17]\n",
        "217": "December 2016[17]\n",
        "218": "August 2018[17]\n",
        "219": "April 2015[156]\n",
        "220": "April 2017[17]\n",
        "221": "March 2019[157]\n",
        "222": "February 2020[158]\n",
        "223": "January 2020[159]\n",
        "224": "August 2019[160]\n",
        "225": "August 2019[161]\n",
        "226": "April 2019[162]\n",
        "227": "March 2019[163]\n",
        "228": "April 2018[17]\n",
        "229": "September 2017[17]\n",
        "230": "July 2016[164]\n",
        "231": "October 2019[165]",
        "232": "May 2019[166]\n",
        "233": "February 2019[167]\n",
        "234": "November 2019\n",
        "235": "November 2019[168]\n",
        "236": "Oct 2019[169]\n",
        "237": "December 2019[170]\n",
        "238": "October 2019[171]\n",
        "239": "October 2019[172]\n",
        "240": "September 2019[173]\n",
        "241": "September 2017[174]\n",
        "242": "July 2019[175]\n",
        "243": "July 2019[176]\n",
        "244": "June 2019[177]\n",
        "245": "June 2019[178]\n",
        "246": "May 2019[179]\n",
        "247": "May 2019[180]\n",
        "248": "May 2019[181]\n",
        "249": "April 2019[182][183]\n",
        "250": "April 2019[184]\n",
        "251": "March 2019[185]\n",
        "252": "April 2019[186]\n",
        "253": "September 2015[187]\n",
        "254": "May 2017[188]\n",
        "255": "August 2018[189]\n",
        "256": "February 2019[190]\n",
        "257": "September 2019[191]\n",
        "258": "July 2019\n",
        "259": "May 2016[192]\n",
        "260": "September 2018[193]\n",
        "261": "May 2019[194]\n",
        "262": "July 2018[195]\n",
        "263": "March 2019[196]\n",
        "264": "May 2018[197][198]\n",
        "265": "March 2019[199]\n",
        "266": "February 2020[200]\n",
        "267": "September 2018[201]\n",
        "268": "June 2016[17]\n",
        "269": "March 2019[202][203]\n",
        "270": "June 2018[204]\n",
        "271": "May 2017[17]\n",
        "272": "June 2017[17]\n",
        "273": "April 2018[17]\n",
        "274": "June 2017[17]\n",
        "275": "January 2018[17]\n",
        "276": "September 2015[17]\n",
        "277": "April 2015[17]\n",
        "278": "May 2018[17]\n",
        "279": "December 2015[205]\n",
        "280": "May 2017[5]\n",
        "281": "February 2020[206]\n",
        "282": "July 2016[17]\n",
        "283": "April 2018[17]\n",
        "284": "August 2016[17]\n",
        "285": "October 2018[207]\n",
        "286": "February 2015[17]\n",
        "287": "May 2018[17]\n",
        "288": "October 2017[17]\n",
        "289": "February 2017[17]\n",
        "290": "October 2016[17]\n",
        "291": "December 2016[208]\n",
        "292": "December 2017[17]\n",
        "293": "October 2015[17]\n",
        "294": "April 2016[17]\n",
        "295": "November 2016[17]\n",
        "296": "June 2017[17]\n",
        "297": "December 2018[209]\n",
        "298": "May 2015[17]\n",
        "299": "October 2017[17]\n",
        "300": "July 2018[17]\n",
        "301": "July 2018[17]\n",
        "302": "December 2017[17]\n",
        "303": "May 2017[210]\n",
        "304": "October 2015[17]\n",
        "305": "November 2017[17]\n",
        "306": "September 2017[17]\n",
        "307": "May 2017[17]\n",
        "308": "August 2015[211]\n",
        "309": "July 2018[17]\n",
        "310": "October 2017[17]\n",
        "311": "August 2017[212]\n",
        "312": "February 2016[213]\n",
        "313": "July 2017[17]\n",
        "314": "April 2017[17]\n",
        "315": "July 2018[17]\n",
        "316": "March 2018[17]\n",
        "317": "September 2017[214]\n",
        "318": "September 2017[215]\n",
        "319": "December 2017[17]\n",
        "320": "November 2017[216]\n",
        "321": "October 2015[17]\n",
        "322": "August 2014[217]\n",
        "323": "July 2014[218]\n",
        "324": "March 2018[17]\n",
        "325": "November 2015[219]\n",
        "326": "January 2015[17]\n",
        "327": "February 2018[220]\n",
        "328": "February 2018[221]\n",
        "329": "May 2017[222]\n",
        "330": "May 2018[223]\n",
        "331": "August 2018[224]\n",
        "332": "October 2018[225]\n",
        "333": "October 2018[226]\n",
        "334": "October 2015[227]\n",
        "335": "February 2019\n",
        "336": "January 2019[228]\n",
        "337": "May 2019[229]\n",
        "338": "June 2019[230]\n",
        "339": "June 2019[231]\n",
        "340": "July 2019[232]\n",
        "341": "July 2019[233]\n",
        "342": "July 2019[234]\n",
        "343": "January 2020[235]\n",
        "344": "August 2019[236]\n",
        "345": "September 2019[citation needed]\n",
        "346": "July 2018[237]\n",
        "347": "July 2019[238]\n"
    },
    {
        "0": " China\n",
        "1": " China\n",
        "2": " China\n",
        "3": " US\n",
        "4": " US\n",
        "5": " US\n",
        "6": " China\n",
        "7": " US\n",
        "8": " China\n",
        "9": " US\n",
        "10": " China\n",
        "11": " India\n",
        "12": " China\n",
        "13": " US\n",
        "14": " Singapore\n",
        "15": " China\n",
        "16": " US\n",
        "17": " China\n",
        "18": " Brazil\n",
        "19": " India\n",
        "20": " Indonesia\n",
        "21": " India\n",
        "22": " China\n",
        "23": " South Korea\n",
        "24": " China\n",
        "25": " US\n",
        "26": " Canada\n",
        "27": " US\n",
        "28": " US\n",
        "29": " China\n",
        "30": " US\n",
        "31": " Indonesia\n",
        "32": "  Switzerland\n",
        "33": " US /  Romania\n",
        "34": " US\n",
        "35": " US\n",
        "36": " US\n",
        "37": " Portugal /  UK\n",
        "38": " US\n",
        "39": " Sweden\n",
        "40": " India\n",
        "41": " US\n",
        "42": " US\n",
        "43": " South Korea\n",
        "44": " China\n",
        "45": " US\n",
        "46": " US\n",
        "47": " China\n",
        "48": " US\n",
        "49": " China\n",
        "50": " South Korea\n",
        "51": " China\n",
        "52": " US\n",
        "53": " US\n",
        "54": " China\n",
        "55": " US\n",
        "56": " US\n",
        "57": " Singapore\n",
        "58": " US\n",
        "59": " China\n",
        "60": " Germany\n",
        "61": " UK\n",
        "62": " US\n",
        "63": " India\n",
        "64": " US\n",
        "65": " China\n",
        "66": " Australia\n",
        "67": " US\n",
        "68": " US\n",
        "69": " US\n",
        "70": " Colombia\n",
        "71": " US\n",
        "72": " China\n",
        "73": " China\n",
        "74": " China\n",
        "75": " China\n",
        "76": " China\n",
        "77": " China\n",
        "78": " China\n",
        "79": " China\n",
        "80": " China\n",
        "81": " China\n",
        "82": " US\n",
        "83": " Indonesia\n",
        "84": " UK\n",
        "85": " China\n",
        "86": " India\n",
        "87": " US\n",
        "88": " US\n",
        "89": " Ukraine\n",
        "90": " US\n",
        "91": " US\n",
        "92": " US\n",
        "93": " US\n",
        "94": " South Korea\n",
        "95": " US\n",
        "96": " Indonesia\n",
        "97": " UK\n",
        "98": " US\n",
        "99": " China\n",
        "100": " US\n",
        "101": " India\n",
        "102": " China\n",
        "103": " China\n",
        "104": " US\n",
        "105": " US\n",
        "106": " US\n",
        "107": " China\n",
        "108": " South Korea\n",
        "109": " China\n",
        "110": " US\n",
        "111": " China\n",
        "112": " UK\n",
        "113": " Germany\n",
        "114": " US\n",
        "115": " China\n",
        "116": " UK\n",
        "117": " US\n",
        "118": " China\n",
        "119": " China\n",
        "120": " China\n",
        "121": " China\n",
        "122": " UK\n",
        "123": " India\n",
        "124": " China\n",
        "125": " US\n",
        "126": " China\n",
        "127": " Indonesia\n",
        "128": " China\n",
        "129": " China\n",
        "130": " China\n",
        "131": " US\n",
        "132": " China\n",
        "133": " US\n",
        "134": " US\n",
        "135": " China\n",
        "136": " China\n",
        "137": " China\n",
        "138": " US /  Israel\n",
        "139": "  Switzerland\n",
        "140": " US\n",
        "141": " US\n",
        "142": " South Korea\n",
        "143": " US\n",
        "144": " China\n",
        "145": " UK\n",
        "146": " Russia\n",
        "147": " India\n",
        "148": " China\n",
        "149": " Chile\n",
        "150": " US\n",
        "151": " US\n",
        "152": " US\n",
        "153": " US\n",
        "154": " US\n",
        "155": " South Korea\n",
        "156": " US\n",
        "157": " US\n",
        "158": " US\n",
        "159": " US\n",
        "160": " UK\n",
        "161": " China\n",
        "162": " US\n",
        "163": " US\n",
        "164": " India\n",
        "165": " China\n",
        "166": " China\n",
        "167": " Sweden\n",
        "168": " France\n",
        "169": " US\n",
        "170": " US\n",
        "171": " US\n",
        "172": " US\n",
        "173": " Israel\n",
        "174": " India\n",
        "175": " India\n",
        "176": " China\n",
        "177": " US\n",
        "178": " China\n",
        "179": " China\n",
        "180": " China\n",
        "181": " China\n",
        "182": " China\n",
        "183": " China\n",
        "184": " China\n",
        "185": " China\n",
        "186": " US\n",
        "187": " Spain\n",
        "188": " US\n",
        "189": " China\n",
        "190": " China\n",
        "191": " China\n",
        "192": " China\n",
        "193": " US\n",
        "194": " US\n",
        "195": " US\n",
        "196": " US\n",
        "197": " India\n",
        "198": " South Korea\n",
        "199": " South Korea\n",
        "200": " US\n",
        "201": " UK\n",
        "202": " China\n",
        "203": " China\n",
        "204": " US\n",
        "205": " US\n",
        "206": " China\n",
        "207": " China\n",
        "208": " US\n",
        "209": " US\n",
        "210": " China\n",
        "211": " UK\n",
        "212": " US\n",
        "213": " India\n",
        "214": " US\n",
        "215": " China\n",
        "216": " China\n",
        "217": " China\n",
        "218": " China\n",
        "219": " US\n",
        "220": " China\n",
        "221": " France\n",
        "222": " US\n",
        "223": " Israel\n",
        "224": " US\n",
        "225": " Japan\n",
        "226": " US\n",
        "227": " US\n",
        "228": " China\n",
        "229": " China\n",
        "230": " Luxembourg\n",
        "231": " India\n",
        "232": " Singapore /  Israel\n",
        "233": " US\n",
        "234": " Argentina\n",
        "235": " Lithuania\n",
        "236": " US\n",
        "237": " South Korea\n",
        "238": " Ukraine\n",
        "239": " US\n",
        "240": " Singapore /   Switzerland\n",
        "241": " US\n",
        "242": " US\n",
        "243": " US\n",
        "244": " US\n",
        "245": " France\n",
        "246": " US\n",
        "247": " US\n",
        "248": " US\n",
        "249": " Hong Kong\n",
        "250": " US\n",
        "251": " Hong Kong\n",
        "252": " US\n",
        "253": " US\n",
        "254": " India\n",
        "255": " China\n",
        "256": " South Korea\n",
        "257": " US\n",
        "258": " Israel\n",
        "259": " US\n",
        "260": " US\n",
        "261": " US\n",
        "262": " India\n",
        "263": " US\n",
        "264": " India\n",
        "265": " US\n",
        "266": " Indonesia /  China\n",
        "267": " Israel\n",
        "268": " China\n",
        "269": " Luxembourg\n",
        "270": " Portugal\n",
        "271": " China\n",
        "272": " China\n",
        "273": " China\n",
        "274": " China\n",
        "275": " China\n",
        "276": " China\n",
        "277": " China\n",
        "278": " China\n",
        "279": " US\n",
        "280": " India\n",
        "281": " US\n",
        "282": " China\n",
        "283": " China\n",
        "284": " China\n",
        "285": " US\n",
        "286": " China\n",
        "287": " China\n",
        "288": " China\n",
        "289": " China\n",
        "290": " China\n",
        "291": " UAE\n",
        "292": " China\n",
        "293": " China\n",
        "294": " China\n",
        "295": " China\n",
        "296": " China\n",
        "297": " US\n",
        "298": " China\n",
        "299": " China\n",
        "300": " China\n",
        "301": " China\n",
        "302": " China\n",
        "303": " US\n",
        "304": " China\n",
        "305": " China\n",
        "306": " China\n",
        "307": " China\n",
        "308": " US\n",
        "309": " China\n",
        "310": " China\n",
        "311": " US\n",
        "312": "  Switzerland\n",
        "313": " China\n",
        "314": " China\n",
        "315": " China\n",
        "316": " China\n",
        "317": " Hong Kong\n",
        "318": " US\n",
        "319": " China\n",
        "320": " US\n",
        "321": " China\n",
        "322": " US\n",
        "323": " Canada\n",
        "324": " China\n",
        "325": " US\n",
        "326": " China\n",
        "327": " US\n",
        "328": " Israel\n",
        "329": " UK\n",
        "330": " Estonia\n",
        "331": " US\n",
        "332": " Portugal\n",
        "333": " US\n",
        "334": " US\n",
        "335": " Australia\n",
        "336": " Belgium\n",
        "337": " US\n",
        "338": " Belgium /  Netherlands\n",
        "339": " India\n",
        "340": " India\n",
        "341": " India\n",
        "342": " India /  US\n",
        "343": " India/ US\n",
        "344": " US\n",
        "345": " US\n",
        "346": " India /  US\n",
        "347": " US\n"
    }
]